MANIFEST.in
README.md
requirements.txt
setup.py
biblio/__init__.py
biblio/cli.py
biblio/config.py
biblio/util.py
biblio/walker.py
biblio.egg-info/PKG-INFO
biblio.egg-info/SOURCES.txt
biblio.egg-info/dependency_links.txt
biblio.egg-info/pbr.json
biblio.egg-info/requires.txt
biblio.egg-info/top_level.txt
biblio/outputs/__init__.py
biblio/outputs/base.py
biblio/outputs/json.py
biblio/outputs/html/__init__.py
biblio/outputs/html/static/styles.css
biblio/outputs/html/static/theme.css
biblio/outputs/html/static/theme.js
biblio/outputs/html/templates/arg.html
biblio/outputs/html/templates/base.html
biblio/outputs/html/templates/class.html
biblio/outputs/html/templates/constant.html
biblio/outputs/html/templates/docstring.html
biblio/outputs/html/templates/function.html
biblio/outputs/html/templates/index.html
biblio/outputs/html/templates/module.html
biblio/outputs/markdown/__init__.py
biblio/outputs/markdown/templates/class.md
biblio/outputs/markdown/templates/constant.md
biblio/outputs/markdown/templates/docstring.md
biblio/outputs/markdown/templates/function.md
biblio/outputs/markdown/templates/module.md
biblio/parsers/__init__.py
biblio/parsers/base.py
biblio/parsers/numpy.py